overprint/__init__.py
overprint/__main__.py
overprint-0.0.2.dist-info/METADATA
overprint-0.0.2.dist-info/WHEEL
overprint-0.0.2.dist-info/RECORD
