Metadata-Version: 1.2
Name: overprint
Version: 0.0.2
Summary: Simple nicer command line interface to easily rewrite the previous line of text.
Home-page: https://github.com/Carreau/overprint
License: UNKNOWN
Author: Matthias Bussonnier
Author-email: bussonniermatthias@gmail.com
Classifier: License :: OSI Approved :: MIT License
Requires-Dist: withlog
